[
    {
        "epoch": 1,
        "average_loss": 0.25908990656534553
    },
    {
        "epoch": 101,
        "average_loss": 0.056199916002621766
    },
    {
        "epoch": 201,
        "average_loss": 0.013885474178091592
    },
    {
        "epoch": 301,
        "average_loss": 0.00453452922834662
    },
    {
        "epoch": 401,
        "average_loss": 0.0027211110394171362
    },
    {
        "epoch": 501,
        "average_loss": 0.001956992807604167
    },
    {
        "epoch": 601,
        "average_loss": 0.0015325201999339222
    },
    {
        "epoch": 701,
        "average_loss": 0.0012614526188411117
    },
    {
        "epoch": 801,
        "average_loss": 0.0010732650418461955
    },
    {
        "epoch": 901,
        "average_loss": 0.0009348389542214052
    },
    {
        "epoch": 1001,
        "average_loss": 0.0008276249101794831
    },
    {
        "epoch": 1101,
        "average_loss": 0.0007424179961381554
    },
    {
        "epoch": 1201,
        "average_loss": 0.0006731998511700463
    },
    {
        "epoch": 1301,
        "average_loss": 0.0006159143685977573
    },
    {
        "epoch": 1401,
        "average_loss": 0.0005675831182199989
    },
    {
        "epoch": 1501,
        "average_loss": 0.0005262518086904555
    },
    {
        "epoch": 1601,
        "average_loss": 0.0004903812651754208
    },
    {
        "epoch": 1701,
        "average_loss": 0.0004592847008916958
    },
    {
        "epoch": 1801,
        "average_loss": 0.0004317214617554632
    },
    {
        "epoch": 1901,
        "average_loss": 0.00040730866750410375
    },
    {
        "epoch": 2001,
        "average_loss": 0.00038550555548090993
    },
    {
        "epoch": 2101,
        "average_loss": 0.00036582019483096255
    },
    {
        "epoch": 2201,
        "average_loss": 0.00034810471637238455
    },
    {
        "epoch": 2301,
        "average_loss": 0.00033199046453764267
    },
    {
        "epoch": 2401,
        "average_loss": 0.0003172975231496045
    }
]